till/__init__.py
till/engine.py
till-0.0.1.dist-info/LICENSE
till-0.0.1.dist-info/METADATA
till-0.0.1.dist-info/WHEEL
till-0.0.1.dist-info/top_level.txt
till-0.0.1.dist-info/RECORD
